customdl/__init__.py
customdl/base.py
customdl/fnn.py
customdl-1.0.15.dist-info/LICENSE
customdl-1.0.15.dist-info/METADATA
customdl-1.0.15.dist-info/WHEEL
customdl-1.0.15.dist-info/top_level.txt
customdl-1.0.15.dist-info/RECORD
