Metadata-Version: 2.1
Name: customdl
Version: 1.0.15
Summary: Custom Deep Learning
Home-page: UNKNOWN
Author: Taarak Rapolu
Author-email: taarak.rapolu@gmail.com
License: UNKNOWN
Platform: UNKNOWN
Classifier: Programming Language :: Python :: 3
Classifier: Programming Language :: Python :: 3.6
Classifier: Programming Language :: Python :: 3.7
Classifier: Operating System :: OS Independent
Requires-Python: >=3.6
License-File: LICENSE
Requires-Dist: cycler (==0.10.0)
Requires-Dist: kiwisolver (==1.3.1)
Requires-Dist: matplotlib (==3.3.4)
Requires-Dist: numpy (==1.19.5)
Requires-Dist: Pillow (==8.2.0)
Requires-Dist: pyparsing (==2.4.7)
Requires-Dist: python-dateutil (==2.8.1)
Requires-Dist: six (==1.16.0)
